repo4llm.py
repo4llm-0.1.2.dist-info/LICENSE
repo4llm-0.1.2.dist-info/METADATA
repo4llm-0.1.2.dist-info/WHEEL
repo4llm-0.1.2.dist-info/entry_points.txt
repo4llm-0.1.2.dist-info/top_level.txt
repo4llm-0.1.2.dist-info/RECORD
