Metadata-Version: 2.1
Name: repo4llm
Version: 0.1.2
Summary: A command-line tool to make a code repo digestible for an LLMs
Author-email: lhl <lhl@randomfoo.net>
License: Apache-2.0
Classifier: Programming Language :: Python :: 3
Classifier: License :: OSI Approved :: Apache Software License
Classifier: Operating System :: OS Independent
License-File: LICENSE
Requires-Dist: click
Requires-Dist: scandir
Requires-Dist: toml
